frigg_test_discovery.py
frigg_test_discovery-1.4.1.dist-info/DESCRIPTION.rst
frigg_test_discovery-1.4.1.dist-info/METADATA
frigg_test_discovery-1.4.1.dist-info/RECORD
frigg_test_discovery-1.4.1.dist-info/WHEEL
frigg_test_discovery-1.4.1.dist-info/metadata.json
frigg_test_discovery-1.4.1.dist-info/top_level.txt
