Metadata-Version: 2.0
Name: frigg-test-discovery
Version: 1.4.1
Summary: Test discovery util for frigg-worker
Home-page: https://github.com/frigg/frigg-test-discovery
Author: The frigg team
Author-email: hi@frigg.io
License: MIT
Platform: UNKNOWN
Classifier: Programming Language :: Python :: 3
